kungfu_pandas/__init__.py
kungfu_pandas/kungfu.py
test/__init__.py
test/conftest.py
test/test_agg_col.py
test/test_case_when.py
test/test_count.py
test/test_mask.py
kungfu_pandas-0.1.4.dist-info/LICENSE
kungfu_pandas-0.1.4.dist-info/METADATA
kungfu_pandas-0.1.4.dist-info/WHEEL
kungfu_pandas-0.1.4.dist-info/top_level.txt
kungfu_pandas-0.1.4.dist-info/RECORD
