Metadata-Version: 2.1
Name: kungfu-pandas
Version: 0.1.4
Summary: UNKNOWN
Home-page: UNKNOWN
License: UNKNOWN
Platform: UNKNOWN
Requires: pandas
License-File: LICENSE
Requires-Dist: pandas
Provides-Extra: dev
Requires-Dist: pytest ; extra == 'dev'
Requires-Dist: pandas ; extra == 'dev'
Requires-Dist: pre-commit ; extra == 'dev'
Requires-Dist: twine ; extra == 'dev'
Provides-Extra: docs
Requires-Dist: mkdocs (==1.1) ; extra == 'docs'
Requires-Dist: mkdocs-material (==4.6.3) ; extra == 'docs'
Requires-Dist: mkdocstrings (==0.8.0) ; extra == 'docs'
Provides-Extra: test
Requires-Dist: pytest ; extra == 'test'
Requires-Dist: pandas ; extra == 'test'
